npnet/__init__.py
npnet/activations.py
npnet/dataloader.py
npnet/initializers.py
npnet/layers.py
npnet/losses.py
npnet/metrics.py
npnet/module.py
npnet/optimizers.py
npnet/saver.py
npnet/variable.py
npnet-0.0.10.dist-info/LICENSE
npnet-0.0.10.dist-info/METADATA
npnet-0.0.10.dist-info/WHEEL
npnet-0.0.10.dist-info/top_level.txt
npnet-0.0.10.dist-info/RECORD
