Metadata-Version: 2.1
Name: npnet
Version: 0.0.10
Summary: neural net powered by numpy
Home-page: https://github.com/MorvanZhou/npnet
Author: MorvanZhou
Author-email: mofanpy@hotmail.com
Project-URL: Bug Tracker, https://github.com/MorvanZhou/npnet/issues
Project-URL: Source, https://github.com/MorvanZhou/npnet
Classifier: Programming Language :: Python :: 3
Classifier: License :: OSI Approved :: MIT License
Classifier: Operating System :: OS Independent
Requires-Python: >=3.6
License-File: LICENSE
Requires-Dist: numpy (>=1.19.5) ; python_version < "3.8"
Requires-Dist: numpy (>=1.22.3) ; python_version >= "3.8"
Provides-Extra: build
Requires-Dist: tox (==3.24.3) ; extra == 'build'
Requires-Dist: build ; extra == 'build'
Requires-Dist: twine ; extra == 'build'
Requires-Dist: pylint ; extra == 'build'
Provides-Extra: test
Requires-Dist: tox-conda ; extra == 'test'
Requires-Dist: matplotlib (>=3.3.4) ; extra == 'test'
